mureq/__init__.py
mureq-0.2.0.dist-info/LICENSE
mureq-0.2.0.dist-info/METADATA
mureq-0.2.0.dist-info/WHEEL
mureq-0.2.0.dist-info/top_level.txt
mureq-0.2.0.dist-info/RECORD
