Metadata-Version: 2.1
Name: mureq
Version: 0.2.0
Summary: Single-file alternative to python-requests
Home-page: https://github.com/slingamn/mureq
Author: Shivaram Lingamneni
Author-email: slingamn@cs.stanford.edu
License: UNKNOWN
Project-URL: Bug Tracker, https://github.com/slingamn/mureq/issues
Platform: UNKNOWN
Classifier: Programming Language :: Python :: 3.6
Classifier: Programming Language :: Python :: 3.7
Classifier: Programming Language :: Python :: 3.8
Classifier: Programming Language :: Python :: 3.9
Classifier: Programming Language :: Python :: 3.10
Classifier: Programming Language :: Python :: 3.11
Classifier: License :: OSI Approved :: BSD License
Classifier: Operating System :: OS Independent
Requires-Python: >=3.6
License-File: LICENSE
